script.py
MaizePageContacts-0.0.2.dist-info/LICENSE
MaizePageContacts-0.0.2.dist-info/METADATA
MaizePageContacts-0.0.2.dist-info/WHEEL
MaizePageContacts-0.0.2.dist-info/entry_points.txt
MaizePageContacts-0.0.2.dist-info/top_level.txt
MaizePageContacts-0.0.2.dist-info/RECORD
