Metadata-Version: 2.1
Name: MaizePageContacts
Version: 0.0.2
Summary: Scrape contact information of student-orgs at UMich
Home-page: https://github.com/yangkev/MaizePageContacts
Author: Kevin Yang
Author-email: yangke@umich.edu
License: MIT
Platform: UNKNOWN
Classifier: Programming Language :: Python :: 3
Classifier: License :: OSI Approved :: MIT License
Classifier: Operating System :: OS Independent
Requires-Python: >=3
Requires-Dist: requests (>=2.20.0)
Requires-Dist: beautifulsoup4 (>=4.4.0)
Requires-Dist: urllib3 (>=1.23)
